autofile/__init__.py
autofile/__main__.py
autofile/_version.py
autofile/autofile.py
autofile/cli.py
autofile/constants.py
autofile/datetime_formatter.py
autofile/datetime_utils.py
autofile/exiftool.py
autofile/filetemplate.md
autofile/filetemplate.py
autofile/hookspecs.py
autofile/mtlparser.py
autofile/mtlparser.tx
autofile/path_utils.py
autofile/pathlibutil.py
autofile/renderoptions.py
autofile/utils.py
autofile/plugins/__init__.py
autofile/plugins/templates/__init__.py
autofile/plugins/templates/_finder_macos.py
autofile/plugins/templates/_mdls_macos.py
autofile/plugins/templates/_uti_macos.py
autofile/plugins/templates/audio.py
autofile/plugins/templates/docx.py
autofile/plugins/templates/exiftool.py
autofile/plugins/templates/filedates.py
autofile/plugins/templates/filepath.py
autofile/plugins/templates/filestat.py
autofile/plugins/templates/finder.py
autofile/plugins/templates/mdls.py
autofile/plugins/templates/pdf.py
autofile/plugins/templates/uti.py
autofile-0.1.0.dist-info/LICENSE
autofile-0.1.0.dist-info/METADATA
autofile-0.1.0.dist-info/WHEEL
autofile-0.1.0.dist-info/entry_points.txt
autofile-0.1.0.dist-info/top_level.txt
autofile-0.1.0.dist-info/RECORD
