Metadata-Version: 2.1
Name: autofile
Version: 0.1.0
Summary: Use templates to automatically move files into directories
Home-page: https://github.com/RhetTbull/autofile
Download-URL: https://github.com/RhetTbull/autofile
Author: Rhet Turnbull
Author-email: rturnbull+git@gmail.com
License: License :: OSI Approved :: MIT License
Project-URL: GitHub, https://github.com/RhetTbull/autofile
Classifier: Development Status :: 4 - Beta
Classifier: Environment :: Console
Classifier: Environment :: MacOS X
Classifier: Operating System :: POSIX :: Linux
Classifier: Operating System :: MacOS
Classifier: License :: OSI Approved :: MIT License
Classifier: Intended Audience :: End Users/Desktop
Classifier: Operating System :: MacOS :: MacOS X
Classifier: Programming Language :: Python :: 3.9
Classifier: Programming Language :: Python :: 3.10
Classifier: Programming Language :: Python :: 3.11
Classifier: Programming Language :: Python :: 3.12
Classifier: Programming Language :: Python :: 3.13
Classifier: Topic :: Software Development :: Libraries :: Python Modules
Requires-Python: >=3.9
License-File: LICENSE
Requires-Dist: click>=8.0.1
Requires-Dist: cloup>=0.11.0
Requires-Dist: pathvalidate<4.0.0,>=2.5.0
Requires-Dist: pdfminer.six>=20211012
Requires-Dist: pluggy<=2.0.0,>=1.0.0
Requires-Dist: python-docx<2.0.0,>=0.8.11
Requires-Dist: rich>=11.0.0
Requires-Dist: tenacity<10.0.0,>=8.0.1
Requires-Dist: textX>=2.3.0
Requires-Dist: tinytag<3.0.0,>=1.8.0
Requires-Dist: yaspin<4.0.0,>=2.1.0
Requires-Dist: osxmetadata>=1.3.4
Requires-Dist: pyobjc-core>=7.3
Requires-Dist: pyobjc-framework-Cocoa>=7.3
Requires-Dist: pyobjc-framework-CoreServices>=7.3
Requires-Dist: pyobjc-framework-FSEvents>=7.3
